bypaxpan/__init__.py
bypaxpan-0.1.dist-info/METADATA
bypaxpan-0.1.dist-info/WHEEL
bypaxpan-0.1.dist-info/top_level.txt
bypaxpan-0.1.dist-info/RECORD
